cli_utils/__init__.py
cli_utils/_metadata.py
cli_utils/get_time.py
cli_utils/menu.py
cli_utils/unit_tests/__init__.py
cli_utils/unit_tests/menu_test.py
cli_utils-1.0.6.dist-info/LICENSE.txt
cli_utils-1.0.6.dist-info/METADATA
cli_utils-1.0.6.dist-info/RECORD
cli_utils-1.0.6.dist-info/WHEEL
cli_utils-1.0.6.dist-info/entry_points.txt
cli_utils-1.0.6.dist-info/top_level.txt
